{
    "id": "sub-1778344851159-805",
    "name": "强模移位寄存器",
    "author": "Unknown",
    "tags": [
        "其他杂物",
        "1.16+"
    ],
    "description": "### 🚀 机器概览\n- **核心功能**: 未知\n- **适用版本**: Java 1.16+\n- **投影创建者名称**: Unknown\n- **投影创建时间**: 2026-05-09\n\n### 📖 使用说明\n1. 在非原版特性端使用时，请先测试机器能否正常工作后再进行实装。\n2. 机器介绍：未知",
    "folder": "强模移位寄存器",
    "preview": "preview.webp",
    "filename": "强模移位寄存器t1_hss_hex_shift_register_1_12_v1_2[编码相关].litematic",
    "submitDate": "2026-05-09T16:40:51.159Z"
}